nextion/__init__.py
nextion/client.py
nextion/constants.py
nextion/exceptions.py
nextion/py.typed
nextion/console_scripts/__init__.py
nextion/console_scripts/upload_firmware.py
nextion/protocol/__init__.py
nextion/protocol/base.py
nextion/protocol/nextion.py
nextion-2.0.0.dist-info/LICENSE
nextion-2.0.0.dist-info/METADATA
nextion-2.0.0.dist-info/WHEEL
nextion-2.0.0.dist-info/entry_points.txt
nextion-2.0.0.dist-info/top_level.txt
nextion-2.0.0.dist-info/zip-safe
nextion-2.0.0.dist-info/RECORD
