Metadata-Version: 2.1
Name: nextion
Version: 2.0.0
Summary: Nextion display serial client
Home-page: https://github.com/yozik04/nextion
Author: Jevgeni Kiski
Author-email: yozik04@gmail.com
License: LGPL 3
Project-URL: Bug Tracker, https://github.com/yozik04/nextion/issues
Keywords: nextion serial async asyncio
Classifier: Development Status :: 5 - Production/Stable
Classifier: Intended Audience :: Developers
Classifier: License :: OSI Approved :: GNU Lesser General Public License v3 (LGPLv3)
Classifier: Operating System :: OS Independent
Classifier: Programming Language :: Python
Classifier: Programming Language :: Python :: 3
Requires-Python: <4,>=3.8.0
License-File: LICENSE
Requires-Dist: pyserial-asyncio-fast
